hv_anndata/__init__.py
hv_anndata/accessors.py
hv_anndata/components.py
hv_anndata/interface.py
hv_anndata/manifoldmap.py
hv_anndata/plotting.py
hv_anndata-0.0.2.dist-info/METADATA
hv_anndata-0.0.2.dist-info/WHEEL
hv_anndata-0.0.2.dist-info/licenses/LICENSE
hv_anndata-0.0.2.dist-info/RECORD
